[
  { "x": 2, "y": 32 },
  { "x": 4, "y": 32 },
  { "x": 7, "y": 32 },
  { "x": 11, "y": 32 },
  { "x": 14, "y": 32 },
  { "x": 18, "y": 32 },
  { "x": 22, "y": 32 },
  { "x": 26, "y": 32 },
  { "x": 30, "y": 32 },
  { "x": 33, "y": 32 },
  { "x": 37, "y": 32 },
  { "x": 41, "y": 32 },
  { "x": 45, "y": 32 },
  { "x": 49, "y": 32 },
  { "x": 52, "y": 32 },
  { "x": 56, "y": 32 },
  { "x": 60, "y": 32 },
  { "x": 64, "y": 32 },
  { "x": 68, "y": 32 },
  { "x": 71, "y": 32 },
  { "x": 75, "y": 32 },
  { "x": 79, "y": 32 },
  { "x": 83, "y": 32 },
  { "x": 87, "y": 32 },
  { "x": 90, "y": 32 },
  { "x": 94, "y": 32 },
  { "x": 98, "y": 32 },
  { "x": 102, "y": 32 },
  { "x": 105, "y": 32 },
  { "x": 109, "y": 32 },
  { "x": 113, "y": 32 },
  { "x": 117, "y": 32 },
  { "x": 121, "y": 32 },
  { "x": 125, "y": 32 },
  { "x": 128, "y": 32 },
  { "x": 132, "y": 32 },
  { "x": 136, "y": 32 },
  { "x": 140, "y": 32 },
  { "x": 143, "y": 32 },
  { "x": 147, "y": 32 },
  { "x": 151, "y": 32 },
  { "x": 155, "y": 32 },
  { "x": 159, "y": 32 },
  { "x": 162, "y": 32 },
  { "x": 166, "y": 32 },
  { "x": 170, "y": 32 },
  { "x": 174, "y": 32 },
  { "x": 177, "y": 32 },
  { "x": 181, "y": 32 },
  { "x": 185, "y": 32 },
  { "x": 189, "y": 32 },
  { "x": 193, "y": 32 },
  { "x": 196, "y": 32 },
  { "x": 200, "y": 32 },
  { "x": 204, "y": 32 },
  { "x": 208, "y": 32 },
  { "x": 212, "y": 32 },
  { "x": 215, "y": 32 },
  { "x": 219, "y": 32 },
  { "x": 223, "y": 32 },
  { "x": 227, "y": 32 },
  { "x": 231, "y": 32 },
  { "x": 234, "y": 32 },
  { "x": 238, "y": 32 },
  { "x": 242, "y": 32 },
  { "x": 246, "y": 32 },
  { "x": 250, "y": 32 },
  { "x": 253, "y": 32 },
  { "x": 257, "y": 32 },
  { "x": 261, "y": 32 },
  { "x": 265, "y": 32 },
  { "x": 269, "y": 32 },
  { "x": 272, "y": 32 },
  { "x": 276, "y": 32 },
  { "x": 280, "y": 32 },
  { "x": 284, "y": 32 },
  { "x": 287, "y": 32 },
  { "x": 291, "y": 32 },
  { "x": 295, "y": 32 },
  { "x": 299, "y": 32 },
  { "x": 303, "y": 32 },
  { "x": 306, "y": 32 },
  { "x": 310, "y": 32 },
  { "x": 314, "y": 32 },
  { "x": 318, "y": 32 },
  { "x": 322, "y": 32 },
  { "x": 325, "y": 32 },
  { "x": 329, "y": 32 },
  { "x": 333, "y": 32 },
  { "x": 337, "y": 32 },
  { "x": 341, "y": 32 },
  { "x": 344, "y": 32 },
  { "x": 348, "y": 32 },
  { "x": 352, "y": 32 },
  { "x": 356, "y": 32 },
  { "x": 360, "y": 32 },
  { "x": 363, "y": 32 },
  { "x": 367, "y": 32 },
  { "x": 371, "y": 32 },
  { "x": 375, "y": 32 },
  { "x": 379, "y": 32 },
  { "x": 383, "y": 32 },
  { "x": 386, "y": 32 },
  { "x": 390, "y": 32 },
  { "x": 394, "y": 32 },
  { "x": 397, "y": 32 },
  { "x": 401, "y": 32 },
  { "x": 405, "y": 32 },
  { "x": 409, "y": 32 },
  { "x": 413, "y": 32 },
  { "x": 416, "y": 32 },
  { "x": 420, "y": 32 },
  { "x": 424, "y": 32 },
  { "x": 428, "y": 32 },
  { "x": 432, "y": 32 },
  { "x": 435, "y": 32 },
  { "x": 439, "y": 32 },
  { "x": 443, "y": 32 },
  { "x": 447, "y": 32 },
  { "x": 450, "y": 32 },
  { "x": 454, "y": 32 },
  { "x": 458, "y": 32 },
  { "x": 462, "y": 32 },
  { "x": 466, "y": 32 },
  { "x": 470, "y": 32 },
  { "x": 473, "y": 32 },
  { "x": 477, "y": 32 },
  { "x": 481, "y": 32 },
  { "x": 485, "y": 32 },
  { "x": 489, "y": 32 }
]
